{"cameraMode":{"drawMode":0,"name":"Shaded","section":"Shading Mode"},"sceneLighting":true,"audioPlay":false,"sceneViewState":{"showFog":true,"showMaterialUpdate":false,"showSkybox":true,"showFlares":true,"showImageEffects":true,"showParticleSystems":true},"in2DMode":false,"pivot":{"x":-4.3698577880859379,"y":17.81406593322754,"z":-3.6439170837402345},"rotation":{"x":-0.026981540024280549,"y":0.9187722206115723,"z":-0.06378193199634552,"w":-0.3886663019657135},"size":131.17501831054688,"orthographic":false}